{
  "products": [
    {
      "id": 1,
      "name": "Syltherine",
      "description": "Stylish cafe chair",
      "price": "Rp 2.500.000",
      "discountedPrice": "Rp 3.500.000",
      "badge": "-30%",
      "img": ""
    },
    {
      "id": 2,
      "name": "Leviosa",
      "description": "Stylish cafe chair",
      "price": "Rp 2.500.000",
      "discountedPrice": "",
      "badge": "",
      "img": ""
    },
    {
      "id": 3,
      "name": "Lolito",
      "description": "Luxury big sofa",
      "price": "Rp 7.000.000",
      "discountedPrice": "Rp 14.000.000",
      "badge": "-50%",
      "img": ""
    },
    {
      "id": 4,
      "name": "Respira",
      "description": "Outdoor bar table and stool",
      "price": "Rp 500.000",
      "discountedPrice": "",
      "badge": "New",
      "img": ""
    },
    {
      "id": 5,
      "name": "Grifo",
      "description": "Night lamp",
      "price": "Rp 1.500.000",
      "discountedPrice": "",
      "badge": "",
      "img": ""
    },
    {
      "id": 6,
      "name": "Muggo",
      "description": "Small mug",
      "price": "Rp 150.000",
      "discountedPrice": "",
      "badge": "New",
      "img": ""
    },
    {
      "id": 7,
      "name": "Pingky",
      "description": "Cute bed set",
      "price": "Rp 7.000.000",
      "discountedPrice": "Rp 14.000.000",
      "badge": "-50%",
      "img": ""
    },
    {
      "id": 8,
      "name": "Potty",
      "description": "Minimalist flower pot",
      "price": "Rp 500.000",
      "discountedPrice": "",
      "badge": "New",
      "img": ""
    }
  ]
}
